pyronn_torch_cpp.cpython-35m-x86_64-linux-gnu.so
pyronn_torch/__init__.py
pyronn_torch/codegen.py
pyronn_torch/conebeam.py
pyronn_torch/PYRO-NN-Layers/__init__.py
pyronn_torch/PYRO-NN-Layers/cuda_operator.py
pyronn_torch-0.1.0.dist-info/AUTHORS.rst
pyronn_torch-0.1.0.dist-info/LICENSE.txt
pyronn_torch-0.1.0.dist-info/METADATA
pyronn_torch-0.1.0.dist-info/WHEEL
pyronn_torch-0.1.0.dist-info/top_level.txt
pyronn_torch-0.1.0.dist-info/RECORD
