Metadata-Version: 2.1
Name: pyronn-torch
Version: 0.1.0
Summary: PyTorch bindings for PYRO-NN (https://github.com/csyben/PYRO-NN)
Home-page: https://github.com/theHamsta/pyronn-torch
Author: Stephan Seitz, Christopher Symben
Author-email: stephan.seitz@fau.de, christopher.syben@fau.de
License: GPLv3
Project-URL: Documentation, https://github.com/theHamsta/pyronn-torch
Platform: any
Classifier: Development Status :: 4 - Beta
Classifier: Programming Language :: Python
Requires-Dist: numpy
Requires-Dist: torch
Requires-Dist: sympy
Provides-Extra: testing
Requires-Dist: pytest ; extra == 'testing'
Requires-Dist: pytest-cov ; extra == 'testing'
